chatbot/__init__.py
chatbot/base.py
chatbot/chain.py
chatbot/ui/__init__.py
chatbot/ui/main.py
chatbot/ui/templates.py
llm_inference/__init__.py
llm_inference/model.py
llm_inference/serve.py
llama_inference-0.0.4.dist-info/LICENSE
llama_inference-0.0.4.dist-info/METADATA
llama_inference-0.0.4.dist-info/WHEEL
llama_inference-0.0.4.dist-info/top_level.txt
llama_inference-0.0.4.dist-info/RECORD
