Metadata-Version: 2.1
Name: llama-inference
Version: 0.0.4
Summary: Large Language Models Inference API and Chatbot
Home-page: https://github.com/aniketmaurya/LLaMA-inference-api
Author: Aniket Maurya
Author-email: theaniketmaurya@gmail.com
License: Apache License 2.0
Keywords: LLM,LLaMA,GPT
Requires-Python: >=3.8
License-File: LICENSE
Requires-Dist: python-dotenv
Requires-Dist: lightning (>=2.0.0)
Provides-Extra: chatbot
Requires-Dist: lightning ; extra == 'chatbot'
Requires-Dist: langchain (>=0.0.94) ; extra == 'chatbot'
Requires-Dist: openai (>=0.26.5) ; extra == 'chatbot'
Requires-Dist: streamlit (>=1.19.0) ; extra == 'chatbot'
Requires-Dist: streamlit-chat (>=0.0.2.1) ; extra == 'chatbot'
Requires-Dist: transformers (>=4.26.1) ; extra == 'chatbot'
Requires-Dist: fastapi (>=0.88.0) ; extra == 'chatbot'
